LICENSE
README.rst
pyproject.toml
setup.py
quotequail/__init__.py
quotequail/_enums.py
quotequail/_html.py
quotequail/_internal.py
quotequail/_patterns.py
quotequail.egg-info/PKG-INFO
quotequail.egg-info/SOURCES.txt
quotequail.egg-info/dependency_links.txt
quotequail.egg-info/requires.txt
quotequail.egg-info/top_level.txt