Metadata-Version: 2.1
Name: quotequail
Version: 0.4.0
Summary: A library that identifies quoted text in plain text and HTML email messages.
Home-page: http://github.com/closeio/quotequail
Author: Thomas Steinacher
Author-email: engineering@close.com
Maintainer: Thomas Steinacher
Maintainer-email: engineering@close.com
License: MIT
Platform: any
Classifier: Environment :: Web Environment
Classifier: Intended Audience :: Developers
Classifier: License :: OSI Approved :: MIT License
Classifier: Operating System :: OS Independent
Classifier: Programming Language :: Python
Classifier: Programming Language :: Python :: 3
Classifier: Programming Language :: Python :: 3.10
Classifier: Programming Language :: Python :: 3.11
Classifier: Programming Language :: Python :: 3.12
Classifier: Topic :: Communications :: Email
Classifier: Topic :: Software Development :: Libraries :: Python Modules
License-File: LICENSE
